ifccityjson/__init__.py
ifccityjson/__main__.py
ifccityjson/cityjson2ifc/__init__.py
ifccityjson/cityjson2ifc/cityjson2ifc.py
ifccityjson/cityjson2ifc/geometry.py
ifccityjson-0.8.3.dist-info/METADATA
ifccityjson-0.8.3.dist-info/WHEEL
ifccityjson-0.8.3.dist-info/top_level.txt
ifccityjson-0.8.3.dist-info/RECORD
