Metadata-Version: 2.4
Name: ifccityjson
Version: 0.8.3
Summary: Converter for CityJSON files and IFC
Author-email: "Laurens J.N. Oostwegel" <l.oostwegel@gmail.com>, Balázs Dukai <balazs.dukai@3dgi.nl>
Project-URL: Homepage, http://ifcopenshell.org
Project-URL: Documentation, https://docs.ifcopenshell.org
Project-URL: Issues, https://github.com/IfcOpenShell/IfcOpenShell/issues
Keywords: IFC,CityJSON,BIM
Classifier: Programming Language :: Python :: 3
Classifier: License :: OSI Approved :: GNU Lesser General Public License v3 or later (LGPLv3+)
Requires-Dist: ifcopenshell
Requires-Dist: cjio<0.10,>=0.8
